zorro_pytorch/__init__.py
zorro_pytorch/zorro_pytorch.py
zorro_pytorch-0.1.1.dist-info/LICENSE
zorro_pytorch-0.1.1.dist-info/METADATA
zorro_pytorch-0.1.1.dist-info/WHEEL
zorro_pytorch-0.1.1.dist-info/top_level.txt
zorro_pytorch-0.1.1.dist-info/RECORD
