Metadata-Version: 2.1
Name: zorro-pytorch
Version: 0.1.1
Summary: Zorro - Pytorch
Home-page: https://github.com/lucidrains/zorro-pytorch
Author: Phil Wang
Author-email: lucidrains@gmail.com
License: MIT
Keywords: artificial intelligence,deep learning,transformers,attention mechanism,multimodal fusion
Classifier: Development Status :: 4 - Beta
Classifier: Intended Audience :: Developers
Classifier: Topic :: Scientific/Engineering :: Artificial Intelligence
Classifier: License :: OSI Approved :: MIT License
Classifier: Programming Language :: Python :: 3.6
License-File: LICENSE
Requires-Dist: beartype
Requires-Dist: einops >=0.4
Requires-Dist: torch >=1.6
Requires-Dist: torchaudio
